hikvision_isapi_utils/__init__.py
hikvision_isapi_utils/asyncclient.py
hikvision_isapi_utils/client.py
hikvision_isapi_utils-0.1.1.dist-info/licenses/LICENSE
hikvision_isapi_utils-0.1.1.dist-info/METADATA
hikvision_isapi_utils-0.1.1.dist-info/WHEEL
hikvision_isapi_utils-0.1.1.dist-info/top_level.txt
hikvision_isapi_utils-0.1.1.dist-info/RECORD
