Metadata-Version: 2.4
Name: hikvision-isapi-utils
Version: 0.1.1
Summary: A Python library for interacting with Hikvision devices via ISAPI.
Author-email: sunbo <1443584939@qq.com>
License-Expression: MIT
Project-URL: Homepage, https://github.com/sunbos/hikvision-isapi-utils
Project-URL: Repository, https://github.com/sunbos/hikvision-isapi-utils
Classifier: Development Status :: 3 - Alpha
Classifier: Intended Audience :: Developers
Classifier: Topic :: Software Development :: Libraries
Classifier: Programming Language :: Python :: 3
Classifier: Programming Language :: Python :: 3.8
Classifier: Programming Language :: Python :: 3.9
Classifier: Programming Language :: Python :: 3.10
Classifier: Programming Language :: Python :: 3.11
Classifier: Programming Language :: Python :: 3.12
Requires-Python: >=3.8
License-File: LICENSE
Requires-Dist: requests>=2.25.0
Requires-Dist: httpx>=0.24.0
Dynamic: license-file
